django_session_csrf-0.7.1.dist-info/DESCRIPTION.rst
django_session_csrf-0.7.1.dist-info/METADATA
django_session_csrf-0.7.1.dist-info/RECORD
django_session_csrf-0.7.1.dist-info/WHEEL
django_session_csrf-0.7.1.dist-info/metadata.json
django_session_csrf-0.7.1.dist-info/top_level.txt
session_csrf/__init__.py
session_csrf/models.py
session_csrf/tests.py
